fastdjango/__init__.py
fastdjango/app.py
fastdjango/conf/__init__.py
fastdjango/contrib/__init__.py
fastdjango/contrib/admin/__init__.py
fastdjango/contrib/admin/decorators.py
fastdjango/contrib/admin/filters.py
fastdjango/contrib/admin/inlines.py
fastdjango/contrib/admin/options.py
fastdjango/contrib/admin/routes.py
fastdjango/contrib/admin/site.py
fastdjango/contrib/admin/templates/admin/base.html
fastdjango/contrib/admin/templates/admin/change_form.html
fastdjango/contrib/admin/templates/admin/changelist.html
fastdjango/contrib/admin/templates/admin/index.html
fastdjango/contrib/admin/templates/errors/400.html
fastdjango/contrib/admin/templates/errors/403.html
fastdjango/contrib/admin/templates/errors/404.html
fastdjango/contrib/auth/__init__.py
fastdjango/contrib/auth/backends.py
fastdjango/contrib/auth/decorators.py
fastdjango/contrib/auth/hashers.py
fastdjango/contrib/auth/models.py
fastdjango/contrib/messages/__init__.py
fastdjango/contrib/sessions/__init__.py
fastdjango/contrib/sessions/middleware.py
fastdjango/contrib/sessions/backends/__init__.py
fastdjango/contrib/sessions/backends/base.py
fastdjango/contrib/sessions/backends/db.py
fastdjango/contrib/sessions/backends/signed_cookies.py
fastdjango/core/__init__.py
fastdjango/core/exceptions.py
fastdjango/core/signals.py
fastdjango/core/cache/__init__.py
fastdjango/core/mail/__init__.py
fastdjango/core/management/__init__.py
fastdjango/core/management/commands/__init__.py
fastdjango/core/management/commands/collectstatic.py
fastdjango/core/management/commands/createsuperuser.py
fastdjango/core/management/commands/makemigrations.py
fastdjango/core/management/commands/migrate.py
fastdjango/core/management/commands/runserver.py
fastdjango/core/management/commands/shell.py
fastdjango/core/management/commands/startapp.py
fastdjango/core/management/commands/startproject.py
fastdjango/db/__init__.py
fastdjango/db/fields.py
fastdjango/db/manager.py
fastdjango/db/queryset.py
fastdjango/db/backends/__init__.py
django_fastapi_async-0.2.6.dist-info/METADATA
django_fastapi_async-0.2.6.dist-info/WHEEL
django_fastapi_async-0.2.6.dist-info/entry_points.txt
django_fastapi_async-0.2.6.dist-info/licenses/LICENSE
django_fastapi_async-0.2.6.dist-info/RECORD
