Metadata-Version: 2.4
Name: django-fastapi-async
Version: 0.2.6
Summary: Django-like framework built on FastAPI - 100% async
Project-URL: Homepage, https://github.com/TWFBusiness/fastdjango
Project-URL: Documentation, https://github.com/TWFBusiness/fastdjango#readme
Project-URL: Repository, https://github.com/TWFBusiness/fastdjango.git
Project-URL: Issues, https://github.com/TWFBusiness/fastdjango/issues
Author: FastDjango Team
License: MIT
License-File: LICENSE
Keywords: async,django,fastapi,framework,web
Classifier: Development Status :: 3 - Alpha
Classifier: Framework :: FastAPI
Classifier: Intended Audience :: Developers
Classifier: License :: OSI Approved :: MIT License
Classifier: Programming Language :: Python :: 3.11
Classifier: Programming Language :: Python :: 3.12
Classifier: Topic :: Internet :: WWW/HTTP :: HTTP Servers
Requires-Python: >=3.11
Requires-Dist: aerich>=0.7.2
Requires-Dist: aiofiles>=23.2.1
Requires-Dist: aiosmtplib>=3.0.0
Requires-Dist: aiosqlite<0.20.0,>=0.17.0
Requires-Dist: bcrypt<5.0.0,>=4.0.0
Requires-Dist: email-validator>=2.1.0
Requires-Dist: fastapi>=0.109.0
Requires-Dist: httpx>=0.26.0
Requires-Dist: itsdangerous>=2.1.2
Requires-Dist: jinja2>=3.1.3
Requires-Dist: passlib>=1.7.4
Requires-Dist: pydantic-settings>=2.1.0
Requires-Dist: pydantic>=2.5.0
Requires-Dist: python-jose[cryptography]>=3.3.0
Requires-Dist: python-multipart>=0.0.6
Requires-Dist: rich>=13.7.0
Requires-Dist: tortoise-orm[asyncmy,asyncpg]>=0.20.0
Requires-Dist: typer[all]>=0.9.0
Requires-Dist: uvicorn[standard]>=0.27.0
Requires-Dist: websockets>=12.0
Provides-Extra: dev
Requires-Dist: black>=24.1.0; extra == 'dev'
Requires-Dist: mypy>=1.8.0; extra == 'dev'
Requires-Dist: pre-commit>=3.6.0; extra == 'dev'
Requires-Dist: pytest-asyncio>=0.23.0; extra == 'dev'
Requires-Dist: pytest-cov>=4.1.0; extra == 'dev'
Requires-Dist: pytest>=7.4.0; extra == 'dev'
Requires-Dist: ruff>=0.1.14; extra == 'dev'
